README.txt
bootstrap.py
buildout.cfg
setup.py
collective/.DS_Store
collective/__init__.py
collective.js.nivogallery.egg-info/PKG-INFO
collective.js.nivogallery.egg-info/SOURCES.txt
collective.js.nivogallery.egg-info/dependency_links.txt
collective.js.nivogallery.egg-info/entry_points.txt
collective.js.nivogallery.egg-info/namespace_packages.txt
collective.js.nivogallery.egg-info/not-zip-safe
collective.js.nivogallery.egg-info/requires.txt
collective.js.nivogallery.egg-info/top_level.txt
collective/js/.DS_Store
collective/js/__init__.py
collective/js/nivogallery/.DS_Store
collective/js/nivogallery/__init__.py
collective/js/nivogallery/configure.zcml
collective/js/nivogallery/profiles/.DS_Store
collective/js/nivogallery/profiles/default/jsregistry.xml
collective/js/nivogallery/profiles/default/metadata.xml
collective/js/nivogallery/profiles/uninstall/jsregistry.xml
collective/js/nivogallery/resources/.DS_Store
collective/js/nivogallery/resources/changelog.txt
collective/js/nivogallery/resources/license.txt
collective/js/nivogallery/resources/package.json
collective/js/nivogallery/resources/css/.DS_Store
collective/js/nivogallery/resources/css/arrows.png
collective/js/nivogallery/resources/css/fullscreen.png
collective/js/nivogallery/resources/css/index.html
collective/js/nivogallery/resources/css/loading.gif
collective/js/nivogallery/resources/css/nivo-gallery.css
collective/js/nivogallery/resources/css/playpause.png
collective/js/nivogallery/resources/css/style.css
collective/js/nivogallery/resources/js/jquery.nivo.gallery.js
collective/js/nivogallery/resources/js/jquery.nivo.gallery.min.js
collective/js/nivogallery/resources/js/modernizr-1.7.min.js
collective/js/nivogallery/tests/__init__.py
collective/js/nivogallery/tests/base.py
collective/js/nivogallery/tests/test_setup.py
docs/HISTORY.txt