Metadata-Version: 1.0
Name: collective.js.nivogallery
Version: 1.0
Summary: JQuery Nivogallery plugin as browser resource
Home-page: http://github.com/espenmn/collective.js.nivogallery
Author: Espen Moe-Nillssen
Author-email: espen@medialog.no
License: GPL
Keywords: nivo gallery nivogallery plonetruegallery
Platform: UNKNOWN
Classifier: Programming Language :: Python
